optimization_capstone/.DS_Store
optimization_capstone/__init__.py
optimization_capstone/resource_measurement.py
optimization_capstone-0.0.1.dist-info/METADATA
optimization_capstone-0.0.1.dist-info/WHEEL
optimization_capstone-0.0.1.dist-info/licenses/LICENSE
optimization_capstone-0.0.1.dist-info/RECORD
