Metadata-Version: 2.1
Name: optimization_capstone
Version: 0.0.1
Summary: Python package for Bradley University - Optimization Capstone
Project-URL: Homepage, https://github.com/mthorson-bradley/optimization_capstone
Author-email: Michael Thorson <mthorson@mail.bradley.edu>
License-File: LICENSE
Classifier: License :: OSI Approved :: MIT License
Classifier: Operating System :: OS Independent
Classifier: Programming Language :: Python :: 3
Requires-Python: >=3.7
